{
  "biomes": [
    {
      "name": "Ocean",
      "color": "#0077BE",
      "objects": [
        {
          "name": "Wave",
          "spawnchance": 5,
          "spawnrarity": "Mythical"
        }
      ]
    },
    {
      "name": "Beach",
      "color": "#F2E6A9",
      "objects": [
        {
          "name": "PalmTree",
          "spawnchance": 1,
          "spawnrarity": "Epic"
        }
      ]
    },
    {
      "name": "Tundra",
      "color": "#D3E0FF",
      "objects": [
        {
          "name": "Rock",
          "spawnchance": 1,
          "spawnrarity": "Epic"
        }
      ]
    },
    {
      "name": "Bare",
      "color": "#C2B280"
    },
    {
      "name": "Scorched",
      "color": "#434343",
      "objects": [
        {
          "name": "Rock",
          "spawnchance": 3,
          "spawnrarity": "Epic"
        }
      ]
    },
    {
      "name": "Shrubland",
      "color": "#A9CCB5"
    },
    {
      "name": "Taiga",
      "color": "#354231"
    },
    {
      "name": "TemperateDesert",
      "color": "#E3C089"
    },
    {
      "name": "SubtropicalDesert",
      "color": "#D5B185"
    },
    {
      "name": "Grassland",
      "color": "#9BCB7A",
      "objects": [
        {
          "name": "SwampTree",
          "spawnchance": 2,
          "spawnrarity": "Rare"
        }
      ]
    },
    {
      "name": "TemperateForest",
      "color": "#2D865B",
      "objects": [
        {
          "name": "OakTree",
          "spawnchance": 2
        }
      ]
    },
    {
      "name": "TropicalForest",
      "color": "#2F8F5E",
      "objects": [
        {
          "name": "OakTree",
          "spawnchance": 5
        }
      ]
    },
    {
      "name": "TemperateRainForest",
      "color": "#2C835F",
      "objects": [
        {
          "name": "OakTree",
          "spawnchance": 18
        }
      ]
    },
    {
      "name": "TropicalRainForest",
      "color": "#30815D",
      "objects": [
        {
          "name": "OakTree",
          "spawnchance": 20
        }
      ]
    },
    {
      "name": "Snow",
      "color": "#f7fff9",
      "objects": [
        {
          "name": "Rock",
          "spawnchance": 2,
          "spawnrarity": "Rare"
        }
      ]
    }
  ]
}